richerfilter/__init__.py
richerfilter/filter.py
richerfilter-0.1.0.dist-info/METADATA
richerfilter-0.1.0.dist-info/WHEEL
richerfilter-0.1.0.dist-info/entry_points.txt
richerfilter-0.1.0.dist-info/top_level.txt
richerfilter-0.1.0.dist-info/RECORD
