Metadata-Version: 2.1
Name: richerfilter
Version: 0.1.0
Requires-Dist: opencv-python
Requires-Dist: numpy
